{
  "summary": {
    "total_definitions": 2590,
    "dead_code_candidates": 181,
    "high_confidence": 124,
    "medium_confidence": 0,
    "low_confidence": 57
  },
  "high_confidence": [
    {
      "file": "src/jcodemunch_mcp/_jdocmunch/embeddings/cache.py",
      "qual_name": "purge",
      "short_name": "purge",
      "line": 137,
      "context": "def purge(base_path: Optional[str], owner: str, name: str) -> bool:",
      "confidence": "high",
      "reason": "No references found (short=0, qual=0)",
      "in_tests": false,
      "in_strings": false
    },
    {
      "file": "src/jcodemunch_mcp/_jdocmunch/embeddings/provider.py",
      "qual_name": "_reset_provider_cache",
      "short_name": "_reset_provider_cache",
      "line": 315,
      "context": "def _reset_provider_cache() -> None:",
      "confidence": "high",
      "reason": "No references found (short=0, qual=0)",
      "in_tests": false,
      "in_strings": false
    },
    {
      "file": "src/jcodemunch_mcp/_jdocmunch/embeddings/provider.py",
      "qual_name": "warmup",
      "short_name": "warmup",
      "line": 448,
      "context": "def warmup() -> str:",
      "confidence": "high",
      "reason": "No references found (short=0, qual=0)",
      "in_tests": false,
      "in_strings": false
    },
    {
      "file": "src/jcodemunch_mcp/_jdocmunch/embeddings/provider.py",
      "qual_name": "_reset_query_cache",
      "short_name": "_reset_query_cache",
      "line": 518,
      "context": "def _reset_query_cache() -> None:",
      "confidence": "high",
      "reason": "No references found (short=0, qual=0)",
      "in_tests": false,
      "in_strings": false
    },
    {
      "file": "src/jcodemunch_mcp/_jdocmunch/parser/html_parser.py",
      "qual_name": "_HTMLToTextParser.handle_starttag",
      "short_name": "handle_starttag",
      "line": 44,
      "context": "def handle_starttag(self, tag: str, attrs):",
      "confidence": "high",
      "reason": "No references found (short=0, qual=0)",
      "in_tests": false,
      "in_strings": false
    },
    {
      "file": "src/jcodemunch_mcp/_jdocmunch/parser/html_parser.py",
      "qual_name": "_HTMLToTextParser.handle_endtag",
      "short_name": "handle_endtag",
      "line": 69,
      "context": "def handle_endtag(self, tag: str):",
      "confidence": "high",
      "reason": "No references found (short=0, qual=0)",
      "in_tests": false,
      "in_strings": false
    },
    {
      "file": "src/jcodemunch_mcp/_jdocmunch/parser/html_parser.py",
      "qual_name": "_HTMLToTextParser.handle_data",
      "short_name": "handle_data",
      "line": 88,
      "context": "def handle_data(self, data: str):",
      "confidence": "high",
      "reason": "No references found (short=0, qual=0)",
      "in_tests": false,
      "in_strings": false
    },
    {
      "file": "src/jcodemunch_mcp/_jdocmunch/retrieval/bm25.py",
      "qual_name": "score_section",
      "short_name": "score_section",
      "line": 202,
      "context": "def score_section(",
      "confidence": "high",
      "reason": "No references found (short=0, qual=0)",
      "in_tests": false,
      "in_strings": false
    },
    {
      "file": "src/jcodemunch_mcp/_jdocmunch/retrieval/boilerplate.py",
      "qual_name": "purge",
      "short_name": "purge",
      "line": 171,
      "context": "def purge(base_path: Optional[str], owner: str, name: str) -> bool:",
      "confidence": "high",
      "reason": "No references found (short=0, qual=0)",
      "in_tests": false,
      "in_strings": false
    },
    {
      "file": "src/jcodemunch_mcp/_jdocmunch/retrieval/code_compress.py",
      "qual_name": "compress_fenced_code",
      "short_name": "compress_fenced_code",
      "line": 92,
      "context": "def compress_fenced_code(content: str) -> tuple[str, int]:",
      "confidence": "high",
      "reason": "No references found (short=0, qual=0)",
      "in_tests": false,
      "in_strings": false
    },
    {
      "file": "src/jcodemunch_mcp/_jdocmunch/retrieval/dedup.py",
      "qual_name": "purge",
      "short_name": "purge",
      "line": 232,
      "context": "def purge(base_path: Optional[str], owner: str, name: str) -> bool:",
      "confidence": "high",
      "reason": "No references found (short=0, qual=0)",
      "in_tests": false,
      "in_strings": false
    },
    {
      "file": "src/jcodemunch_mcp/_jdocmunch/retrieval/related_persist.py",
      "qual_name": "purge",
      "short_name": "purge",
      "line": 287,
      "context": "def purge(base_path: Optional[str], owner: str, name: str) -> bool:",
      "confidence": "high",
      "reason": "No references found (short=0, qual=0)",
      "in_tests": false,
      "in_strings": false
    },
    {
      "file": "src/jcodemunch_mcp/_jdocmunch/retrieval/roles.py",
      "qual_name": "annotate_sections",
      "short_name": "annotate_sections",
      "line": 133,
      "context": "def annotate_sections(sections: list) -> list:",
      "confidence": "high",
      "reason": "No references found (short=0, qual=0)",
      "in_tests": false,
      "in_strings": false
    },
    {
      "file": "src/jcodemunch_mcp/_jdocmunch/storage/doc_store.py",
      "qual_name": "DocIndex._word_matches",
      "short_name": "_word_matches",
      "line": 461,
      "context": "def _word_matches(word: str, text: str) -> bool:",
      "confidence": "high",
      "reason": "No references found (short=0, qual=0)",
      "in_tests": false,
      "in_strings": false
    },
    {
      "file": "src/jcodemunch_mcp/_jdocmunch/storage/doc_store.py",
      "qual_name": "_stats_loader",
      "short_name": "_stats_loader",
      "line": 842,
      "context": "def _stats_loader(doc_path: str, byte_start: int, byte_end: int) -> str:",
      "confidence": "high",
      "reason": "No references found (short=1, qual=1)",
      "in_tests": false,
      "in_strings": false
    },
    {
      "file": "src/jcodemunch_mcp/_jdocmunch/storage/replay_log.py",
      "qual_name": "read_all",
      "short_name": "read_all",
      "line": 88,
      "context": "def read_all(base_path: Optional[str] = None, limit: Optional[int] = None) -> list[dict]:",
      "confidence": "high",
      "reason": "No references found (short=0, qual=0)",
      "in_tests": false,
      "in_strings": false
    },
    {
      "file": "src/jcodemunch_mcp/_jdocmunch/storage/token_tracker.py",
      "qual_name": "estimate_savings_text",
      "short_name": "estimate_savings_text",
      "line": 118,
      "context": "def estimate_savings_text(raw: str, response: str) -> int:",
      "confidence": "high",
      "reason": "No references found (short=0, qual=0)",
      "in_tests": false,
      "in_strings": false
    },
    {
      "file": "src/jcodemunch_mcp/_jdocmunch/storage/token_tracker.py",
      "qual_name": "reset_latency_state",
      "short_name": "reset_latency_state",
      "line": 345,
      "context": "def reset_latency_state() -> None:",
      "confidence": "high",
      "reason": "No references found (short=0, qual=0)",
      "in_tests": false,
      "in_strings": false
    },
    {
      "file": "src/jcodemunch_mcp/_jdocmunch/tools/_git.py",
      "qual_name": "local_git_state",
      "short_name": "local_git_state",
      "line": 86,
      "context": "def local_git_state(folder_path: Path, scope_path: Optional[Path] = None) -> tuple[Optional[str], bool]:",
      "confidence": "high",
      "reason": "No references found (short=0, qual=0)",
      "in_tests": false,
      "in_strings": false
    },
    {
      "file": "src/jcodemunch_mcp/_jdocmunch/tools/get_tutorial_path.py",
      "qual_name": "_frontmatter_chain",
      "short_name": "_frontmatter_chain",
      "line": 102,
      "context": "def _frontmatter_chain(store, owner: str, name: str, start_doc: str, doc_paths: set) -> list[str]:",
      "confidence": "high",
      "reason": "No references found (short=1, qual=1)",
      "in_tests": false,
      "in_strings": false
    },
    {
      "file": "src/jcodemunch_mcp/_jdocmunch/tools/get_tutorial_path.py",
      "qual_name": "_inline_link_chain",
      "short_name": "_inline_link_chain",
      "line": 122,
      "context": "def _inline_link_chain(store, owner: str, name: str, start_doc: str, doc_paths: set) -> list[str]:",
      "confidence": "high",
      "reason": "No references found (short=1, qual=1)",
      "in_tests": false,
      "in_strings": false
    },
    {
      "file": "src/jcodemunch_mcp/_jdocmunch/tools/get_tutorial_path.py",
      "qual_name": "_toctree_chain",
      "short_name": "_toctree_chain",
      "line": 152,
      "context": "def _toctree_chain(store, owner: str, name: str, start_doc: str, doc_paths: set) -> list[str]:",
      "confidence": "high",
      "reason": "No references found (short=1, qual=1)",
      "in_tests": false,
      "in_strings": false
    },
    {
      "file": "src/jcodemunch_mcp/_jdocmunch/tools/get_tutorial_path.py",
      "qual_name": "_vuepress_chain",
      "short_name": "_vuepress_chain",
      "line": 212,
      "context": "def _vuepress_chain(store, owner: str, name: str, start_doc: str, doc_paths: set, *, index=None) -> list[str]:",
      "confidence": "high",
      "reason": "No references found (short=1, qual=1)",
      "in_tests": false,
      "in_strings": false
    },
    {
      "file": "src/jcodemunch_mcp/credentials.py",
      "qual_name": "keyring_list",
      "short_name": "keyring_list",
      "line": 134,
      "context": "def keyring_list() -> list[str]:",
      "confidence": "high",
      "reason": "No references found (short=0, qual=0)",
      "in_tests": false,
      "in_strings": false
    },
    {
      "file": "src/jcodemunch_mcp/embeddings/local_encoder.py",
      "qual_name": "_mean_pool",
      "short_name": "_mean_pool",
      "line": 309,
      "context": "def _mean_pool(token_embeddings: list, attention_mask: list) -> list[float]:",
      "confidence": "high",
      "reason": "No references found (short=0, qual=0)",
      "in_tests": false,
      "in_strings": false
    },
    {
      "file": "src/jcodemunch_mcp/encoding/format.py",
      "qual_name": "decode_scalar",
      "short_name": "decode_scalar",
      "line": 141,
      "context": "def decode_scalar(raw: str, type_hint: str = \"str\") -> Any:",
      "confidence": "high",
      "reason": "No references found (short=0, qual=0)",
      "in_tests": false,
      "in_strings": false
    },
    {
      "file": "src/jcodemunch_mcp/enrichment/lsp_bridge.py",
      "qual_name": "LSPServer._read_loop",
      "short_name": "_read_loop",
      "line": 283,
      "context": "def _read_loop(self) -> None:",
      "confidence": "high",
      "reason": "No references found (short=1, qual=0)",
      "in_tests": false,
      "in_strings": false
    },
    {
      "file": "src/jcodemunch_mcp/org/http_routes.py",
      "qual_name": "handle_org_report",
      "short_name": "handle_org_report",
      "line": 43,
      "context": "async def handle_org_report(request: \"Request\") -> \"JSONResponse\":",
      "confidence": "high",
      "reason": "No references found (short=1, qual=1)",
      "in_tests": false,
      "in_strings": false
    },
    {
      "file": "src/jcodemunch_mcp/parser/astro_shared.py",
      "qual_name": "_comment_repl",
      "short_name": "_comment_repl",
      "line": 40,
      "context": "def _comment_repl(match: re.Match[str]) -> str:",
      "confidence": "high",
      "reason": "No references found (short=1, qual=1)",
      "in_tests": false,
      "in_strings": false
    },
    {
      "file": "src/jcodemunch_mcp/parser/context/_route_utils.py",
      "qual_name": "_parse_requirements_txt",
      "short_name": "_parse_requirements_txt",
      "line": 57,
      "context": "def _parse_requirements_txt(content: str) -> set[str]:",
      "confidence": "high",
      "reason": "No references found (short=1, qual=1)",
      "in_tests": false,
      "in_strings": false
    },
    {
      "file": "src/jcodemunch_mcp/parser/context/_route_utils.py",
      "qual_name": "_parse_pyproject_toml_deps",
      "short_name": "_parse_pyproject_toml_deps",
      "line": 74,
      "context": "def _parse_pyproject_toml_deps(content: str) -> set[str]:",
      "confidence": "high",
      "reason": "No references found (short=1, qual=1)",
      "in_tests": false,
      "in_strings": false
    },
    {
      "file": "src/jcodemunch_mcp/parser/context/_route_utils.py",
      "qual_name": "_parse_build_gradle",
      "short_name": "_parse_build_gradle",
      "line": 139,
      "context": "def _parse_build_gradle(content: str) -> set[str]:",
      "confidence": "high",
      "reason": "No references found (short=1, qual=1)",
      "in_tests": false,
      "in_strings": false
    },
    {
      "file": "src/jcodemunch_mcp/parser/context/_route_utils.py",
      "qual_name": "_parse_go_mod",
      "short_name": "_parse_go_mod",
      "line": 151,
      "context": "def _parse_go_mod(content: str) -> set[str]:",
      "confidence": "high",
      "reason": "No references found (short=1, qual=1)",
      "in_tests": false,
      "in_strings": false
    },
    {
      "file": "src/jcodemunch_mcp/parser/context/_route_utils.py",
      "qual_name": "_parse_gemfile",
      "short_name": "_parse_gemfile",
      "line": 173,
      "context": "def _parse_gemfile(content: str) -> set[str]:",
      "confidence": "high",
      "reason": "No references found (short=1, qual=1)",
      "in_tests": false,
      "in_strings": false
    },
    {
      "file": "src/jcodemunch_mcp/parser/context/_route_utils.py",
      "qual_name": "_parse_mix_exs",
      "short_name": "_parse_mix_exs",
      "line": 184,
      "context": "def _parse_mix_exs(content: str) -> set[str]:",
      "confidence": "high",
      "reason": "No references found (short=1, qual=1)",
      "in_tests": false,
      "in_strings": false
    },
    {
      "file": "src/jcodemunch_mcp/parser/extractor.py",
      "qual_name": "_disambiguate_overloads",
      "short_name": "_disambiguate_overloads",
      "line": 1869,
      "context": "def _disambiguate_overloads(symbols: list[Symbol]) -> list[Symbol]:",
      "confidence": "high",
      "reason": "No references found (short=0, qual=0)",
      "in_tests": false,
      "in_strings": false
    },
    {
      "file": "src/jcodemunch_mcp/parser/imports.py",
      "qual_name": "_extract_python_imports",
      "short_name": "_extract_python_imports",
      "line": 257,
      "context": "def _extract_python_imports(content: str) -> list[dict]:",
      "confidence": "high",
      "reason": "No references found (short=1, qual=1)",
      "in_tests": false,
      "in_strings": false
    },
    {
      "file": "src/jcodemunch_mcp/parser/imports.py",
      "qual_name": "_extract_go_imports",
      "short_name": "_extract_go_imports",
      "line": 285,
      "context": "def _extract_go_imports(content: str) -> list[dict]:",
      "confidence": "high",
      "reason": "No references found (short=1, qual=1)",
      "in_tests": false,
      "in_strings": false
    },
    {
      "file": "src/jcodemunch_mcp/parser/imports.py",
      "qual_name": "_extract_rust_imports",
      "short_name": "_extract_rust_imports",
      "line": 318,
      "context": "def _extract_rust_imports(content: str) -> list[dict]:",
      "confidence": "high",
      "reason": "No references found (short=1, qual=1)",
      "in_tests": false,
      "in_strings": false
    },
    {
      "file": "src/jcodemunch_mcp/parser/imports.py",
      "qual_name": "_extract_asm_imports",
      "short_name": "_extract_asm_imports",
      "line": 344,
      "context": "def _extract_asm_imports(content: str) -> list[dict]:",
      "confidence": "high",
      "reason": "No references found (short=1, qual=1)",
      "in_tests": false,
      "in_strings": false
    },
    {
      "file": "src/jcodemunch_mcp/parser/imports.py",
      "qual_name": "_extract_vhdl_imports",
      "short_name": "_extract_vhdl_imports",
      "line": 350,
      "context": "def _extract_vhdl_imports(content: str) -> list[dict]:",
      "confidence": "high",
      "reason": "No references found (short=1, qual=1)",
      "in_tests": false,
      "in_strings": false
    },
    {
      "file": "src/jcodemunch_mcp/parser/imports.py",
      "qual_name": "_extract_verilog_imports",
      "short_name": "_extract_verilog_imports",
      "line": 366,
      "context": "def _extract_verilog_imports(content: str) -> list[dict]:",
      "confidence": "high",
      "reason": "No references found (short=1, qual=1)",
      "in_tests": false,
      "in_strings": false
    },
    {
      "file": "src/jcodemunch_mcp/parser/imports.py",
      "qual_name": "_extract_ruby_imports",
      "short_name": "_extract_ruby_imports",
      "line": 373,
      "context": "def _extract_ruby_imports(content: str) -> list[dict]:",
      "confidence": "high",
      "reason": "No references found (short=1, qual=1)",
      "in_tests": false,
      "in_strings": false
    },
    {
      "file": "src/jcodemunch_mcp/parser/imports.py",
      "qual_name": "_extract_csharp_imports",
      "short_name": "_extract_csharp_imports",
      "line": 379,
      "context": "def _extract_csharp_imports(content: str) -> list[dict]:",
      "confidence": "high",
      "reason": "No references found (short=1, qual=1)",
      "in_tests": false,
      "in_strings": false
    },
    {
      "file": "src/jcodemunch_mcp/parser/imports.py",
      "qual_name": "_extract_php_imports",
      "short_name": "_extract_php_imports",
      "line": 389,
      "context": "def _extract_php_imports(content: str) -> list[dict]:",
      "confidence": "high",
      "reason": "No references found (short=1, qual=1)",
      "in_tests": false,
      "in_strings": false
    },
    {
      "file": "src/jcodemunch_mcp/parser/imports.py",
      "qual_name": "_extract_swift_imports",
      "short_name": "_extract_swift_imports",
      "line": 401,
      "context": "def _extract_swift_imports(content: str) -> list[dict]:",
      "confidence": "high",
      "reason": "No references found (short=1, qual=1)",
      "in_tests": false,
      "in_strings": false
    },
    {
      "file": "src/jcodemunch_mcp/parser/imports.py",
      "qual_name": "_extract_scala_imports",
      "short_name": "_extract_scala_imports",
      "line": 407,
      "context": "def _extract_scala_imports(content: str) -> list[dict]:",
      "confidence": "high",
      "reason": "No references found (short=1, qual=1)",
      "in_tests": false,
      "in_strings": false
    },
    {
      "file": "src/jcodemunch_mcp/parser/imports.py",
      "qual_name": "_extract_haskell_imports",
      "short_name": "_extract_haskell_imports",
      "line": 419,
      "context": "def _extract_haskell_imports(content: str) -> list[dict]:",
      "confidence": "high",
      "reason": "No references found (short=1, qual=1)",
      "in_tests": false,
      "in_strings": false
    },
    {
      "file": "src/jcodemunch_mcp/parser/imports.py",
      "qual_name": "_extract_dart_imports",
      "short_name": "_extract_dart_imports",
      "line": 430,
      "context": "def _extract_dart_imports(content: str) -> list[dict]:",
      "confidence": "high",
      "reason": "No references found (short=1, qual=1)",
      "in_tests": false,
      "in_strings": false
    },
    {
      "file": "src/jcodemunch_mcp/parser/imports.py",
      "qual_name": "_extract_sql_dbt_imports",
      "short_name": "_extract_sql_dbt_imports",
      "line": 445,
      "context": "def _extract_sql_dbt_imports(content: str) -> list[dict]:",
      "confidence": "high",
      "reason": "No references found (short=1, qual=1)",
      "in_tests": false,
      "in_strings": false
    },
    {
      "file": "src/jcodemunch_mcp/parser/imports.py",
      "qual_name": "_extract_vue_imports",
      "short_name": "_extract_vue_imports",
      "line": 659,
      "context": "def _extract_vue_imports(content: str) -> list[dict]:",
      "confidence": "high",
      "reason": "No references found (short=1, qual=1)",
      "in_tests": false,
      "in_strings": false
    },
    {
      "file": "src/jcodemunch_mcp/parser/imports.py",
      "qual_name": "_extract_astro_imports",
      "short_name": "_extract_astro_imports",
      "line": 683,
      "context": "def _extract_astro_imports(content: str) -> list[dict]:",
      "confidence": "high",
      "reason": "No references found (short=1, qual=1)",
      "in_tests": false,
      "in_strings": false
    },
    {
      "file": "src/jcodemunch_mcp/parser/imports.py",
      "qual_name": "_clear_python_roots_cache",
      "short_name": "_clear_python_roots_cache",
      "line": 1028,
      "context": "def _clear_python_roots_cache() -> None:",
      "confidence": "high",
      "reason": "No references found (short=0, qual=0)",
      "in_tests": false,
      "in_strings": false
    },
    {
      "file": "src/jcodemunch_mcp/parser/languages.py",
      "qual_name": "get_language_extensions",
      "short_name": "get_language_extensions",
      "line": 2097,
      "context": "def get_language_extensions() -> dict[str, str]:",
      "confidence": "high",
      "reason": "No references found (short=0, qual=0)",
      "in_tests": false,
      "in_strings": false
    },
    {
      "file": "src/jcodemunch_mcp/redact.py",
      "qual_name": "_replacer",
      "short_name": "_replacer",
      "line": 138,
      "context": "def _replacer(m: re.Match, _label: str = label) -> str:",
      "confidence": "high",
      "reason": "No references found (short=1, qual=1)",
      "in_tests": false,
      "in_strings": false
    },
    {
      "file": "src/jcodemunch_mcp/reindex_state.py",
      "qual_name": "has_any_reindex_state",
      "short_name": "has_any_reindex_state",
      "line": 215,
      "context": "def has_any_reindex_state() -> bool:",
      "confidence": "high",
      "reason": "No references found (short=0, qual=0)",
      "in_tests": false,
      "in_strings": false
    },
    {
      "file": "src/jcodemunch_mcp/retrieval/confidence.py",
      "qual_name": "extract_ledger_features",
      "short_name": "extract_ledger_features",
      "line": 146,
      "context": "def extract_ledger_features(scored_results: list[dict]) -> dict:",
      "confidence": "high",
      "reason": "No references found (short=0, qual=0)",
      "in_tests": false,
      "in_strings": false
    },
    {
      "file": "src/jcodemunch_mcp/retrieval/regret.py",
      "qual_name": "analyze_regret",
      "short_name": "analyze_regret",
      "line": 195,
      "context": "def analyze_regret(",
      "confidence": "high",
      "reason": "No references found (short=0, qual=0)",
      "in_tests": false,
      "in_strings": false
    },
    {
      "file": "src/jcodemunch_mcp/retrieval/tuning.py",
      "qual_name": "WeightTuner.learn",
      "short_name": "learn",
      "line": 236,
      "context": "def learn(",
      "confidence": "high",
      "reason": "No references found (short=0, qual=0)",
      "in_tests": false,
      "in_strings": false
    },
    {
      "file": "src/jcodemunch_mcp/runtime/http_routes.py",
      "qual_name": "handle_otel",
      "short_name": "handle_otel",
      "line": 279,
      "context": "async def handle_otel(request: \"Request\") -> \"JSONResponse\":",
      "confidence": "high",
      "reason": "No references found (short=1, qual=1)",
      "in_tests": false,
      "in_strings": false
    },
    {
      "file": "src/jcodemunch_mcp/runtime/http_routes.py",
      "qual_name": "handle_sql",
      "short_name": "handle_sql",
      "line": 308,
      "context": "async def handle_sql(request: \"Request\") -> \"JSONResponse\":",
      "confidence": "high",
      "reason": "No references found (short=1, qual=1)",
      "in_tests": false,
      "in_strings": false
    },
    {
      "file": "src/jcodemunch_mcp/runtime/http_routes.py",
      "qual_name": "handle_stack",
      "short_name": "handle_stack",
      "line": 341,
      "context": "async def handle_stack(request: \"Request\") -> \"JSONResponse\":",
      "confidence": "high",
      "reason": "No references found (short=1, qual=1)",
      "in_tests": false,
      "in_strings": false
    },
    {
      "file": "src/jcodemunch_mcp/runtime/ingest.py",
      "qual_name": "_BatchAggregator.mapped_count",
      "short_name": "mapped_count",
      "line": 197,
      "context": "def mapped_count(self) -> int:",
      "confidence": "high",
      "reason": "No references found (short=1, qual=0)",
      "in_tests": false,
      "in_strings": false
    },
    {
      "file": "src/jcodemunch_mcp/runtime/ingest.py",
      "qual_name": "_BatchAggregator.unmapped_count",
      "short_name": "unmapped_count",
      "line": 201,
      "context": "def unmapped_count(self) -> int:",
      "confidence": "high",
      "reason": "No references found (short=1, qual=0)",
      "in_tests": false,
      "in_strings": false
    },
    {
      "file": "src/jcodemunch_mcp/runtime/redact.py",
      "qual_name": "_sub_secret",
      "short_name": "_sub_secret",
      "line": 141,
      "context": "def _sub_secret(m: re.Match, _label: str = label) -> str:",
      "confidence": "high",
      "reason": "No references found (short=1, qual=1)",
      "in_tests": false,
      "in_strings": false
    },
    {
      "file": "src/jcodemunch_mcp/runtime/redact.py",
      "qual_name": "_sub_trace",
      "short_name": "_sub_trace",
      "line": 150,
      "context": "def _sub_trace(m: re.Match, _label: str = label) -> str:",
      "confidence": "high",
      "reason": "No references found (short=1, qual=1)",
      "in_tests": false,
      "in_strings": false
    },
    {
      "file": "src/jcodemunch_mcp/runtime/sql_ingest.py",
      "qual_name": "_BatchAggregator.mapped_call_total",
      "short_name": "mapped_call_total",
      "line": 381,
      "context": "def mapped_call_total(self) -> int:",
      "confidence": "high",
      "reason": "No references found (short=1, qual=0)",
      "in_tests": false,
      "in_strings": false
    },
    {
      "file": "src/jcodemunch_mcp/runtime/sql_ingest.py",
      "qual_name": "_BatchAggregator.unmapped_call_total",
      "short_name": "unmapped_call_total",
      "line": 385,
      "context": "def unmapped_call_total(self) -> int:",
      "confidence": "high",
      "reason": "No references found (short=1, qual=0)",
      "in_tests": false,
      "in_strings": false
    },
    {
      "file": "src/jcodemunch_mcp/runtime/sql_ingest.py",
      "qual_name": "_BatchAggregator.column_total",
      "short_name": "column_total",
      "line": 389,
      "context": "def column_total(self) -> int:",
      "confidence": "high",
      "reason": "No references found (short=1, qual=0)",
      "in_tests": false,
      "in_strings": false
    },
    {
      "file": "src/jcodemunch_mcp/runtime/stack_ingest.py",
      "qual_name": "_BatchAggregator.mapped_total",
      "short_name": "mapped_total",
      "line": 203,
      "context": "def mapped_total(self) -> int:",
      "confidence": "high",
      "reason": "No references found (short=1, qual=0)",
      "in_tests": false,
      "in_strings": false
    },
    {
      "file": "src/jcodemunch_mcp/runtime/stack_ingest.py",
      "qual_name": "_BatchAggregator.unmapped_total",
      "short_name": "unmapped_total",
      "line": 207,
      "context": "def unmapped_total(self) -> int:",
      "confidence": "high",
      "reason": "No references found (short=1, qual=0)",
      "in_tests": false,
      "in_strings": false
    },
    {
      "file": "src/jcodemunch_mcp/server.py",
      "qual_name": "_emit_tools_list_changed",
      "short_name": "_emit_tools_list_changed",
      "line": 640,
      "context": "async def _emit_tools_list_changed() -> None:",
      "confidence": "high",
      "reason": "No references found (short=0, qual=0)",
      "in_tests": false,
      "in_strings": false
    },
    {
      "file": "src/jcodemunch_mcp/server.py",
      "qual_name": "_save_session_state",
      "short_name": "_save_session_state",
      "line": 857,
      "context": "def _save_session_state() -> None:",
      "confidence": "high",
      "reason": "No references found (short=1, qual=1)",
      "in_tests": false,
      "in_strings": false
    },
    {
      "file": "src/jcodemunch_mcp/server.py",
      "qual_name": "_cleanup_mermaid_temp_shutdown",
      "short_name": "_cleanup_mermaid_temp_shutdown",
      "line": 943,
      "context": "def _cleanup_mermaid_temp_shutdown() -> None:",
      "confidence": "high",
      "reason": "No references found (short=1, qual=1)",
      "in_tests": false,
      "in_strings": false
    },
    {
      "file": "src/jcodemunch_mcp/server.py",
      "qual_name": "handle_sse",
      "short_name": "handle_sse",
      "line": 4258,
      "context": "async def handle_sse(request: Request):",
      "confidence": "high",
      "reason": "No references found (short=1, qual=1)",
      "in_tests": false,
      "in_strings": false
    },
    {
      "file": "src/jcodemunch_mcp/server.py",
      "qual_name": "cfg_row",
      "short_name": "cfg_row",
      "line": 4801,
      "context": "def cfg_row(name, key, default, source=None, fmt=None):",
      "confidence": "high",
      "reason": "No references found (short=0, qual=0)",
      "in_tests": false,
      "in_strings": false
    },
    {
      "file": "src/jcodemunch_mcp/storage/index_store.py",
      "qual_name": "IndexStore._write_checksum",
      "short_name": "_write_checksum",
      "line": 425,
      "context": "def _write_checksum(self, index_path: Path, index_bytes: bytes) -> None:",
      "confidence": "high",
      "reason": "No references found (short=0, qual=0)",
      "in_tests": false,
      "in_strings": false
    },
    {
      "file": "src/jcodemunch_mcp/storage/index_store.py",
      "qual_name": "IndexStore._verify_checksum",
      "short_name": "_verify_checksum",
      "line": 433,
      "context": "def _verify_checksum(self, index_path: Path) -> bool:",
      "confidence": "high",
      "reason": "No references found (short=0, qual=0)",
      "in_tests": false,
      "in_strings": false
    },
    {
      "file": "src/jcodemunch_mcp/storage/index_store.py",
      "qual_name": "IndexStore._write_meta_sidecar",
      "short_name": "_write_meta_sidecar",
      "line": 456,
      "context": "def _write_meta_sidecar(self, index: \"CodeIndex\") -> None:",
      "confidence": "high",
      "reason": "No references found (short=0, qual=0)",
      "in_tests": false,
      "in_strings": false
    },
    {
      "file": "src/jcodemunch_mcp/storage/index_store.py",
      "qual_name": "IndexStore._repo_metadata_from_data",
      "short_name": "_repo_metadata_from_data",
      "line": 513,
      "context": "def _repo_metadata_from_data(self, data: dict, owner: str, name: str) -> tuple[str, str, str]:",
      "confidence": "high",
      "reason": "No references found (short=0, qual=0)",
      "in_tests": false,
      "in_strings": false
    },
    {
      "file": "src/jcodemunch_mcp/storage/index_store.py",
      "qual_name": "IndexStore._languages_from_symbols",
      "short_name": "_languages_from_symbols",
      "line": 816,
      "context": "def _languages_from_symbols(self, symbols: list[dict]) -> dict[str, int]:",
      "confidence": "high",
      "reason": "No references found (short=0, qual=0)",
      "in_tests": false,
      "in_strings": false
    },
    {
      "file": "src/jcodemunch_mcp/storage/token_tracker.py",
      "qual_name": "get_total_encoding_saved",
      "short_name": "get_total_encoding_saved",
      "line": 644,
      "context": "def get_total_encoding_saved(base_path: Optional[str] = None) -> int:",
      "confidence": "high",
      "reason": "No references found (short=0, qual=0)",
      "in_tests": false,
      "in_strings": false
    },
    {
      "file": "src/jcodemunch_mcp/storage/token_tracker.py",
      "qual_name": "perf_db_query",
      "short_name": "perf_db_query",
      "line": 865,
      "context": "def perf_db_query(",
      "confidence": "high",
      "reason": "No references found (short=0, qual=0)",
      "in_tests": false,
      "in_strings": false
    },
    {
      "file": "src/jcodemunch_mcp/tools/assemble_task_context.py",
      "qual_name": "_stage_orientation",
      "short_name": "_stage_orientation",
      "line": 408,
      "context": "def _stage_orientation() -> None:",
      "confidence": "high",
      "reason": "No references found (short=1, qual=1)",
      "in_tests": false,
      "in_strings": false
    },
    {
      "file": "src/jcodemunch_mcp/tools/assemble_task_context.py",
      "qual_name": "_stage_hotspots",
      "short_name": "_stage_hotspots",
      "line": 412,
      "context": "def _stage_hotspots() -> None:",
      "confidence": "high",
      "reason": "No references found (short=1, qual=1)",
      "in_tests": false,
      "in_strings": false
    },
    {
      "file": "src/jcodemunch_mcp/tools/assemble_task_context.py",
      "qual_name": "_stage_tectonic",
      "short_name": "_stage_tectonic",
      "line": 430,
      "context": "def _stage_tectonic() -> None:",
      "confidence": "high",
      "reason": "No references found (short=1, qual=1)",
      "in_tests": false,
      "in_strings": false
    },
    {
      "file": "src/jcodemunch_mcp/tools/assemble_task_context.py",
      "qual_name": "_stage_anchor",
      "short_name": "_stage_anchor",
      "line": 462,
      "context": "def _stage_anchor() -> None:",
      "confidence": "high",
      "reason": "No references found (short=1, qual=1)",
      "in_tests": false,
      "in_strings": false
    },
    {
      "file": "src/jcodemunch_mcp/tools/assemble_task_context.py",
      "qual_name": "_stage_callers",
      "short_name": "_stage_callers",
      "line": 480,
      "context": "def _stage_callers() -> None:",
      "confidence": "high",
      "reason": "No references found (short=1, qual=1)",
      "in_tests": false,
      "in_strings": false
    },
    {
      "file": "src/jcodemunch_mcp/tools/assemble_task_context.py",
      "qual_name": "_stage_callees",
      "short_name": "_stage_callees",
      "line": 515,
      "context": "def _stage_callees() -> None:",
      "confidence": "high",
      "reason": "No references found (short=1, qual=1)",
      "in_tests": false,
      "in_strings": false
    },
    {
      "file": "src/jcodemunch_mcp/tools/assemble_task_context.py",
      "qual_name": "_stage_blast",
      "short_name": "_stage_blast",
      "line": 550,
      "context": "def _stage_blast() -> None:",
      "confidence": "high",
      "reason": "No references found (short=1, qual=1)",
      "in_tests": false,
      "in_strings": false
    },
    {
      "file": "src/jcodemunch_mcp/tools/assemble_task_context.py",
      "qual_name": "_stage_runtime",
      "short_name": "_stage_runtime",
      "line": 589,
      "context": "def _stage_runtime() -> None:",
      "confidence": "high",
      "reason": "No references found (short=1, qual=1)",
      "in_tests": false,
      "in_strings": false
    },
    {
      "file": "src/jcodemunch_mcp/tools/assemble_task_context.py",
      "qual_name": "_stage_delete_safe",
      "short_name": "_stage_delete_safe",
      "line": 623,
      "context": "def _stage_delete_safe() -> None:",
      "confidence": "high",
      "reason": "No references found (short=1, qual=1)",
      "in_tests": false,
      "in_strings": false
    },
    {
      "file": "src/jcodemunch_mcp/tools/assemble_task_context.py",
      "qual_name": "_stage_implementations",
      "short_name": "_stage_implementations",
      "line": 652,
      "context": "def _stage_implementations() -> None:",
      "confidence": "high",
      "reason": "No references found (short=1, qual=1)",
      "in_tests": false,
      "in_strings": false
    },
    {
      "file": "src/jcodemunch_mcp/tools/assemble_task_context.py",
      "qual_name": "_stage_similar",
      "short_name": "_stage_similar",
      "line": 690,
      "context": "def _stage_similar() -> None:",
      "confidence": "high",
      "reason": "No references found (short=1, qual=1)",
      "in_tests": false,
      "in_strings": false
    },
    {
      "file": "src/jcodemunch_mcp/tools/assemble_task_context.py",
      "qual_name": "_stage_decorators",
      "short_name": "_stage_decorators",
      "line": 728,
      "context": "def _stage_decorators() -> None:",
      "confidence": "high",
      "reason": "No references found (short=1, qual=1)",
      "in_tests": false,
      "in_strings": false
    },
    {
      "file": "src/jcodemunch_mcp/tools/assemble_task_context.py",
      "qual_name": "_stage_risk",
      "short_name": "_stage_risk",
      "line": 752,
      "context": "def _stage_risk() -> None:",
      "confidence": "high",
      "reason": "No references found (short=1, qual=1)",
      "in_tests": false,
      "in_strings": false
    },
    {
      "file": "src/jcodemunch_mcp/tools/assemble_task_context.py",
      "qual_name": "_stage_dead_code_hint",
      "short_name": "_stage_dead_code_hint",
      "line": 773,
      "context": "def _stage_dead_code_hint() -> None:",
      "confidence": "high",
      "reason": "No references found (short=1, qual=1)",
      "in_tests": false,
      "in_strings": false
    },
    {
      "file": "src/jcodemunch_mcp/tools/assemble_task_context.py",
      "qual_name": "_stage_untested",
      "short_name": "_stage_untested",
      "line": 807,
      "context": "def _stage_untested() -> None:",
      "confidence": "high",
      "reason": "No references found (short=1, qual=1)",
      "in_tests": false,
      "in_strings": false
    },
    {
      "file": "src/jcodemunch_mcp/tools/assemble_task_context.py",
      "qual_name": "_stage_changed",
      "short_name": "_stage_changed",
      "line": 851,
      "context": "def _stage_changed() -> None:",
      "confidence": "high",
      "reason": "No references found (short=1, qual=1)",
      "in_tests": false,
      "in_strings": false
    },
    {
      "file": "src/jcodemunch_mcp/tools/assemble_task_context.py",
      "qual_name": "_stage_similar_changed",
      "short_name": "_stage_similar_changed",
      "line": 876,
      "context": "def _stage_similar_changed() -> None:",
      "confidence": "high",
      "reason": "No references found (short=1, qual=1)",
      "in_tests": false,
      "in_strings": false
    },
    {
      "file": "src/jcodemunch_mcp/tools/find_implementations.py",
      "qual_name": "_impl_rank",
      "short_name": "_impl_rank",
      "line": 480,
      "context": "def _impl_rank(rec: dict) -> tuple:",
      "confidence": "high",
      "reason": "No references found (short=1, qual=1)",
      "in_tests": false,
      "in_strings": false
    },
    {
      "file": "src/jcodemunch_mcp/tools/find_similar_symbols.py",
      "qual_name": "_rank_key",
      "short_name": "_rank_key",
      "line": 440,
      "context": "def _rank_key(idx: int) -> tuple:",
      "confidence": "high",
      "reason": "No references found (short=1, qual=1)",
      "in_tests": false,
      "in_strings": false
    },
    {
      "file": "src/jcodemunch_mcp/tools/index_folder.py",
      "qual_name": "get_filtered_files",
      "short_name": "get_filtered_files",
      "line": 84,
      "context": "def get_filtered_files(path: str) -> Generator[str, None, None]:",
      "confidence": "high",
      "reason": "No references found (short=0, qual=0)",
      "in_tests": false,
      "in_strings": false
    },
    {
      "file": "src/jcodemunch_mcp/tools/index_folder.py",
      "qual_name": "_load_all_gitignores",
      "short_name": "_load_all_gitignores",
      "line": 110,
      "context": "def _load_all_gitignores(root: Path) -> dict[Path, pathspec.PathSpec]:",
      "confidence": "high",
      "reason": "No references found (short=0, qual=0)",
      "in_tests": false,
      "in_strings": false
    },
    {
      "file": "src/jcodemunch_mcp/tools/index_folder.py",
      "qual_name": "_is_gitignored",
      "short_name": "_is_gitignored",
      "line": 188,
      "context": "def _is_gitignored(",
      "confidence": "high",
      "reason": "No references found (short=0, qual=0)",
      "in_tests": false,
      "in_strings": false
    },
    {
      "file": "src/jcodemunch_mcp/tools/index_folder.py",
      "qual_name": "_hash_file",
      "short_name": "_hash_file",
      "line": 1930,
      "context": "def _hash_file(rel_path: str) -> str:",
      "confidence": "high",
      "reason": "No references found (short=1, qual=1)",
      "in_tests": false,
      "in_strings": false
    },
    {
      "file": "src/jcodemunch_mcp/tools/mermaid_viewer.py",
      "qual_name": "open_diagram",
      "short_name": "open_diagram",
      "line": 106,
      "context": "def open_diagram(mermaid: str, storage_path: Path | None = None) -> dict:",
      "confidence": "high",
      "reason": "No references found (short=0, qual=0)",
      "in_tests": false,
      "in_strings": false
    },
    {
      "file": "src/jcodemunch_mcp/tools/package_registry.py",
      "qual_name": "invalidate_registry_cache",
      "short_name": "invalidate_registry_cache",
      "line": 369,
      "context": "def invalidate_registry_cache() -> None:",
      "confidence": "high",
      "reason": "No references found (short=0, qual=0)",
      "in_tests": false,
      "in_strings": false
    },
    {
      "file": "src/jcodemunch_mcp/tools/package_registry.py",
      "qual_name": "resolve_cross_repo_file",
      "short_name": "resolve_cross_repo_file",
      "line": 394,
      "context": "def resolve_cross_repo_file(",
      "confidence": "high",
      "reason": "No references found (short=0, qual=0)",
      "in_tests": false,
      "in_strings": false
    },
    {
      "file": "src/jcodemunch_mcp/tools/search_ast.py",
      "qual_name": "_detect_empty_catch",
      "short_name": "_detect_empty_catch",
      "line": 256,
      "context": "def _detect_empty_catch(node, lang: str, source_bytes: bytes) -> list[dict]:",
      "confidence": "high",
      "reason": "No references found (short=1, qual=1)",
      "in_tests": false,
      "in_strings": false
    },
    {
      "file": "src/jcodemunch_mcp/tools/search_ast.py",
      "qual_name": "_detect_bare_except",
      "short_name": "_detect_bare_except",
      "line": 300,
      "context": "def _detect_bare_except(node, lang: str, source_bytes: bytes) -> list[dict]:",
      "confidence": "high",
      "reason": "No references found (short=1, qual=1)",
      "in_tests": false,
      "in_strings": false
    },
    {
      "file": "src/jcodemunch_mcp/tools/search_ast.py",
      "qual_name": "_detect_todo_fixme",
      "short_name": "_detect_todo_fixme",
      "line": 419,
      "context": "def _detect_todo_fixme(node, lang: str, source_bytes: bytes) -> list[dict]:",
      "confidence": "high",
      "reason": "No references found (short=1, qual=1)",
      "in_tests": false,
      "in_strings": false
    },
    {
      "file": "src/jcodemunch_mcp/tools/search_ast.py",
      "qual_name": "_detect_eval_exec",
      "short_name": "_detect_eval_exec",
      "line": 457,
      "context": "def _detect_eval_exec(node, lang: str, source_bytes: bytes) -> list[dict]:",
      "confidence": "high",
      "reason": "No references found (short=1, qual=1)",
      "in_tests": false,
      "in_strings": false
    },
    {
      "file": "src/jcodemunch_mcp/tools/search_ast.py",
      "qual_name": "_detect_hardcoded_secret",
      "short_name": "_detect_hardcoded_secret",
      "line": 490,
      "context": "def _detect_hardcoded_secret(node, lang: str, source_bytes: bytes) -> list[dict]:",
      "confidence": "high",
      "reason": "No references found (short=1, qual=1)",
      "in_tests": false,
      "in_strings": false
    },
    {
      "file": "src/jcodemunch_mcp/tools/search_ast.py",
      "qual_name": "_detect_magic_number",
      "short_name": "_detect_magic_number",
      "line": 524,
      "context": "def _detect_magic_number(node, lang: str, source_bytes: bytes) -> list[dict]:",
      "confidence": "high",
      "reason": "No references found (short=1, qual=1)",
      "in_tests": false,
      "in_strings": false
    },
    {
      "file": "src/jcodemunch_mcp/tools/search_ast.py",
      "qual_name": "_detect_god_function",
      "short_name": "_detect_god_function",
      "line": 563,
      "context": "def _detect_god_function(node, lang: str, source_bytes: bytes) -> list[dict]:",
      "confidence": "high",
      "reason": "No references found (short=1, qual=1)",
      "in_tests": false,
      "in_strings": false
    },
    {
      "file": "src/jcodemunch_mcp/tools/search_ast.py",
      "qual_name": "_detect_reassigned_param",
      "short_name": "_detect_reassigned_param",
      "line": 594,
      "context": "def _detect_reassigned_param(node, lang: str, source_bytes: bytes) -> list[dict]:",
      "confidence": "high",
      "reason": "No references found (short=1, qual=1)",
      "in_tests": false,
      "in_strings": false
    },
    {
      "file": "src/jcodemunch_mcp/tools/search_symbols.py",
      "qual_name": "_get_tokens",
      "short_name": "_get_tokens",
      "line": 2454,
      "context": "def _get_tokens(sym):",
      "confidence": "high",
      "reason": "No references found (short=1, qual=1)",
      "in_tests": false,
      "in_strings": false
    },
    {
      "file": "src/jcodemunch_mcp/tools/search_symbols.py",
      "qual_name": "_get_tokens_fusion",
      "short_name": "_get_tokens_fusion",
      "line": 2670,
      "context": "def _get_tokens_fusion(sym):",
      "confidence": "high",
      "reason": "No references found (short=1, qual=1)",
      "in_tests": false,
      "in_strings": false
    },
    {
      "file": "src/jcodemunch_mcp/tools/session_state.py",
      "qual_name": "load_live_journal",
      "short_name": "load_live_journal",
      "line": 302,
      "context": "def load_live_journal(",
      "confidence": "high",
      "reason": "No references found (short=0, qual=0)",
      "in_tests": false,
      "in_strings": false
    },
    {
      "file": "src/jcodemunch_mcp/tools/turn_budget.py",
      "qual_name": "TurnBudget.is_enabled",
      "short_name": "is_enabled",
      "line": 100,
      "context": "def is_enabled(self) -> bool:",
      "confidence": "high",
      "reason": "No references found (short=0, qual=0)",
      "in_tests": false,
      "in_strings": false
    },
    {
      "file": "src/jcodemunch_mcp/watch_all.py",
      "qual_name": "_request_stop",
      "short_name": "_request_stop",
      "line": 59,
      "context": "def _request_stop() -> None:",
      "confidence": "high",
      "reason": "No references found (short=1, qual=1)",
      "in_tests": false,
      "in_strings": false
    },
    {
      "file": "src/jcodemunch_mcp/watch_all.py",
      "qual_name": "storage_path_default",
      "short_name": "storage_path_default",
      "line": 156,
      "context": "def storage_path_default() -> str:",
      "confidence": "high",
      "reason": "No references found (short=0, qual=0)",
      "in_tests": false,
      "in_strings": false
    },
    {
      "file": "src/jcodemunch_mcp/watcher.py",
      "qual_name": "update_reindex_time",
      "short_name": "update_reindex_time",
      "line": 929,
      "context": "def update_reindex_time() -> None:",
      "confidence": "high",
      "reason": "No references found (short=1, qual=1)",
      "in_tests": false,
      "in_strings": false
    }
  ],
  "medium_confidence": [],
  "low_confidence": [
    {
      "file": "src/jcodemunch_mcp/_jdocmunch/parser/sections.py",
      "qual_name": "Section.from_dict",
      "short_name": "from_dict",
      "line": 74,
      "context": "def from_dict(cls, data: dict) -> \"Section\":",
      "confidence": "low (test usage)",
      "reason": "No references found (short=0, qual=0) [USED IN TESTS]",
      "in_tests": true,
      "in_strings": false
    },
    {
      "file": "src/jcodemunch_mcp/_jdocmunch/retrieval/tuning.py",
      "qual_name": "reset_cache",
      "short_name": "reset_cache",
      "line": 119,
      "context": "def reset_cache() -> None:",
      "confidence": "low (test usage)",
      "reason": "No references found (short=0, qual=0) [USED IN TESTS]",
      "in_tests": true,
      "in_strings": false
    },
    {
      "file": "src/jcodemunch_mcp/_jdocmunch/security.py",
      "qual_name": "safe_decode",
      "short_name": "safe_decode",
      "line": 170,
      "context": "def safe_decode(data: bytes, encoding: str = \"utf-8\") -> str:",
      "confidence": "low (test usage)",
      "reason": "No references found (short=0, qual=0) [USED IN TESTS]",
      "in_tests": true,
      "in_strings": false
    },
    {
      "file": "src/jcodemunch_mcp/_jdocmunch/security.py",
      "qual_name": "should_exclude_file",
      "short_name": "should_exclude_file",
      "line": 180,
      "context": "def should_exclude_file(",
      "confidence": "low (test usage)",
      "reason": "No references found (short=0, qual=0) [USED IN TESTS]",
      "in_tests": true,
      "in_strings": false
    },
    {
      "file": "src/jcodemunch_mcp/_jdocmunch/storage/token_tracker.py",
      "qual_name": "_post",
      "short_name": "_post",
      "line": 43,
      "context": "def _post() -> None:",
      "confidence": "low (test usage)",
      "reason": "No references found (short=1, qual=1) [USED IN TESTS]",
      "in_tests": true,
      "in_strings": false
    },
    {
      "file": "src/jcodemunch_mcp/cli/init.py",
      "qual_name": "print_status",
      "short_name": "print_status",
      "line": 1819,
      "context": "def print_status(",
      "confidence": "low (test usage)",
      "reason": "No references found (short=0, qual=0) [USED IN TESTS]",
      "in_tests": true,
      "in_strings": false
    },
    {
      "file": "src/jcodemunch_mcp/cli/init.py",
      "qual_name": "list_targets",
      "short_name": "list_targets",
      "line": 1861,
      "context": "def list_targets() -> None:",
      "confidence": "low (string ref)",
      "reason": "No references found (short=0, qual=0) [USED IN STRINGS]",
      "in_tests": false,
      "in_strings": true
    },
    {
      "file": "src/jcodemunch_mcp/cli/skills.py",
      "qual_name": "skill_status",
      "short_name": "skill_status",
      "line": 251,
      "context": "def skill_status(scope: str) -> dict:",
      "confidence": "low (test usage)",
      "reason": "No references found (short=0, qual=0) [USED IN TESTS]",
      "in_tests": true,
      "in_strings": false
    },
    {
      "file": "src/jcodemunch_mcp/embeddings/local_encoder.py",
      "qual_name": "reset_session",
      "short_name": "reset_session",
      "line": 299,
      "context": "def reset_session() -> None:",
      "confidence": "low (test usage)",
      "reason": "No references found (short=0, qual=0) [USED IN TESTS]",
      "in_tests": true,
      "in_strings": false
    },
    {
      "file": "src/jcodemunch_mcp/parser/context/dbt.py",
      "qual_name": "_replace",
      "short_name": "_replace",
      "line": 63,
      "context": "def _replace(match: re.Match) -> str:",
      "confidence": "low (test usage)",
      "reason": "No references found (short=1, qual=1) [USED IN TESTS]",
      "in_tests": true,
      "in_strings": false
    },
    {
      "file": "src/jcodemunch_mcp/parser/fqn.py",
      "qual_name": "symbol_to_fqn",
      "short_name": "symbol_to_fqn",
      "line": 13,
      "context": "def symbol_to_fqn(symbol_id: str, psr4_map: dict[str, str]) -> Optional[str]:",
      "confidence": "low (test usage)",
      "reason": "No references found (short=0, qual=0) [USED IN TESTS]",
      "in_tests": true,
      "in_strings": false
    },
    {
      "file": "src/jcodemunch_mcp/parser/parse_cache.py",
      "qual_name": "cached_parse_file",
      "short_name": "cached_parse_file",
      "line": 113,
      "context": "def cached_parse_file(",
      "confidence": "low (test usage)",
      "reason": "No references found (short=0, qual=0) [USED IN TESTS]",
      "in_tests": true,
      "in_strings": true
    },
    {
      "file": "src/jcodemunch_mcp/parser/template_shared.py",
      "qual_name": "_repl",
      "short_name": "_repl",
      "line": 179,
      "context": "def _repl(match: \"re.Match[str]\") -> str:",
      "confidence": "low (test usage)",
      "reason": "No references found (short=1, qual=1) [USED IN TESTS]",
      "in_tests": true,
      "in_strings": false
    },
    {
      "file": "src/jcodemunch_mcp/progress.py",
      "qual_name": "ProgressReporter.finish",
      "short_name": "finish",
      "line": 80,
      "context": "def finish(self, detail: str = \"Complete\") -> None:",
      "confidence": "low (test usage)",
      "reason": "No references found (short=0, qual=0) [USED IN TESTS]",
      "in_tests": true,
      "in_strings": false
    },
    {
      "file": "src/jcodemunch_mcp/reindex_state.py",
      "qual_name": "get_reindex_status",
      "short_name": "get_reindex_status",
      "line": 174,
      "context": "def get_reindex_status(repo: str) -> dict:",
      "confidence": "low (test usage)",
      "reason": "No references found (short=0, qual=0) [USED IN TESTS]",
      "in_tests": true,
      "in_strings": false
    },
    {
      "file": "src/jcodemunch_mcp/reindex_state.py",
      "qual_name": "is_any_reindex_in_progress",
      "short_name": "is_any_reindex_in_progress",
      "line": 209,
      "context": "def is_any_reindex_in_progress() -> bool:",
      "confidence": "low (test usage)",
      "reason": "No references found (short=0, qual=0) [USED IN TESTS]",
      "in_tests": true,
      "in_strings": false
    },
    {
      "file": "src/jcodemunch_mcp/reindex_state.py",
      "qual_name": "await_freshness_if_strict",
      "short_name": "await_freshness_if_strict",
      "line": 246,
      "context": "def await_freshness_if_strict(repo: str, timeout_ms: int = 500) -> bool:",
      "confidence": "low (test usage)",
      "reason": "No references found (short=1, qual=1) [USED IN TESTS]",
      "in_tests": true,
      "in_strings": false
    },
    {
      "file": "src/jcodemunch_mcp/reindex_state.py",
      "qual_name": "wait_for_fresh_result",
      "short_name": "wait_for_fresh_result",
      "line": 270,
      "context": "def wait_for_fresh_result(",
      "confidence": "low (test usage)",
      "reason": "No references found (short=0, qual=0) [USED IN TESTS]",
      "in_tests": true,
      "in_strings": false
    },
    {
      "file": "src/jcodemunch_mcp/retrieval/freshness.py",
      "qual_name": "_clear_head_cache",
      "short_name": "_clear_head_cache",
      "line": 56,
      "context": "def _clear_head_cache() -> None:",
      "confidence": "low (test usage)",
      "reason": "No references found (short=0, qual=0) [USED IN TESTS]",
      "in_tests": true,
      "in_strings": false
    },
    {
      "file": "src/jcodemunch_mcp/runtime/confidence.py",
      "qual_name": "attach_runtime_confidence",
      "short_name": "attach_runtime_confidence",
      "line": 193,
      "context": "def attach_runtime_confidence(",
      "confidence": "low (test usage)",
      "reason": "No references found (short=0, qual=0) [USED IN TESTS]",
      "in_tests": true,
      "in_strings": true
    },
    {
      "file": "src/jcodemunch_mcp/security.py",
      "qual_name": "safe_decode",
      "short_name": "safe_decode",
      "line": 302,
      "context": "def safe_decode(data: bytes, encoding: str = \"utf-8\") -> str:",
      "confidence": "low (test usage)",
      "reason": "No references found (short=0, qual=0) [USED IN TESTS]",
      "in_tests": true,
      "in_strings": false
    },
    {
      "file": "src/jcodemunch_mcp/security.py",
      "qual_name": "should_exclude_file",
      "short_name": "should_exclude_file",
      "line": 406,
      "context": "def should_exclude_file(",
      "confidence": "low (test usage)",
      "reason": "No references found (short=0, qual=0) [USED IN TESTS]",
      "in_tests": true,
      "in_strings": false
    },
    {
      "file": "src/jcodemunch_mcp/server.py",
      "qual_name": "BearerAuthMiddleware.dispatch",
      "short_name": "dispatch",
      "line": 4161,
      "context": "async def dispatch(self, request, call_next):",
      "confidence": "low (test usage)",
      "reason": "No references found (short=0, qual=0) [USED IN TESTS]",
      "in_tests": true,
      "in_strings": false
    },
    {
      "file": "src/jcodemunch_mcp/server.py",
      "qual_name": "RateLimitMiddleware.dispatch",
      "short_name": "dispatch",
      "line": 4207,
      "context": "async def dispatch(self, request, call_next):",
      "confidence": "low (test usage)",
      "reason": "No references found (short=0, qual=0) [USED IN TESTS]",
      "in_tests": true,
      "in_strings": false
    },
    {
      "file": "src/jcodemunch_mcp/server.py",
      "qual_name": "handle_mcp",
      "short_name": "handle_mcp",
      "line": 4402,
      "context": "async def handle_mcp(request: Request):",
      "confidence": "low (test usage)",
      "reason": "No references found (short=1, qual=1) [USED IN TESTS]",
      "in_tests": true,
      "in_strings": false
    },
    {
      "file": "src/jcodemunch_mcp/server.py",
      "qual_name": "_ProjectAwareCfg.__getattr__",
      "short_name": "__getattr__",
      "line": 4705,
      "context": "def __getattr__(self, name):",
      "confidence": "low (test usage)",
      "reason": "No references found (short=0, qual=0) [USED IN TESTS]",
      "in_tests": true,
      "in_strings": false
    },
    {
      "file": "src/jcodemunch_mcp/storage/embedding_store.py",
      "qual_name": "EmbeddingStore.delete_many",
      "short_name": "delete_many",
      "line": 215,
      "context": "def delete_many(self, symbol_ids: list[str]) -> None:",
      "confidence": "low (test usage)",
      "reason": "No references found (short=0, qual=0) [USED IN TESTS]",
      "in_tests": true,
      "in_strings": false
    },
    {
      "file": "src/jcodemunch_mcp/storage/index_store.py",
      "qual_name": "CodeIndex.get_callers_by_name",
      "short_name": "get_callers_by_name",
      "line": 210,
      "context": "def get_callers_by_name(self) -> dict[tuple[str, str], list[str]]:",
      "confidence": "low (test usage)",
      "reason": "No references found (short=0, qual=0) [USED IN TESTS]",
      "in_tests": true,
      "in_strings": true
    },
    {
      "file": "src/jcodemunch_mcp/storage/process_locks.py",
      "qual_name": "LockHolder.as_dict",
      "short_name": "as_dict",
      "line": 139,
      "context": "def as_dict(self) -> dict:",
      "confidence": "low (test usage)",
      "reason": "No references found (short=0, qual=0) [USED IN TESTS]",
      "in_tests": true,
      "in_strings": false
    },
    {
      "file": "src/jcodemunch_mcp/storage/sqlite_store.py",
      "qual_name": "_cache_clear",
      "short_name": "_cache_clear",
      "line": 317,
      "context": "def _cache_clear() -> None:",
      "confidence": "low (test usage)",
      "reason": "No references found (short=0, qual=0) [USED IN TESTS]",
      "in_tests": true,
      "in_strings": false
    },
    {
      "file": "src/jcodemunch_mcp/storage/sqlite_store.py",
      "qual_name": "SQLiteIndexStore.checkpoint_and_close",
      "short_name": "checkpoint_and_close",
      "line": 673,
      "context": "def checkpoint_and_close(self, owner: str, name: str) -> None:",
      "confidence": "low (test usage)",
      "reason": "No references found (short=0, qual=0) [USED IN TESTS]",
      "in_tests": true,
      "in_strings": false
    },
    {
      "file": "src/jcodemunch_mcp/storage/token_tracker.py",
      "qual_name": "write_pulse",
      "short_name": "write_pulse",
      "line": 658,
      "context": "def write_pulse(tool_name: str, tokens_saved: int = 0, base_path: Optional[str] = None) -> None:",
      "confidence": "low (test usage)",
      "reason": "No references found (short=0, qual=0) [USED IN TESTS]",
      "in_tests": true,
      "in_strings": true
    },
    {
      "file": "src/jcodemunch_mcp/storage/token_tracker.py",
      "qual_name": "result_cache_invalidate",
      "short_name": "result_cache_invalidate",
      "line": 773,
      "context": "def result_cache_invalidate(repo: Optional[str] = None) -> int:",
      "confidence": "low (test usage)",
      "reason": "No references found (short=0, qual=0) [USED IN TESTS]",
      "in_tests": true,
      "in_strings": true
    },
    {
      "file": "src/jcodemunch_mcp/storage/token_tracker.py",
      "qual_name": "result_cache_stats",
      "short_name": "result_cache_stats",
      "line": 778,
      "context": "def result_cache_stats() -> dict:",
      "confidence": "low (test usage)",
      "reason": "No references found (short=0, qual=0) [USED IN TESTS]",
      "in_tests": true,
      "in_strings": true
    },
    {
      "file": "src/jcodemunch_mcp/summarizer/batch_summarize.py",
      "qual_name": "summarize_symbols_simple",
      "short_name": "summarize_symbols_simple",
      "line": 840,
      "context": "def summarize_symbols_simple(symbols: list[Symbol]) -> list[Symbol]:",
      "confidence": "low (test usage)",
      "reason": "No references found (short=0, qual=0) [USED IN TESTS]",
      "in_tests": true,
      "in_strings": true
    },
    {
      "file": "src/jcodemunch_mcp/tools/assemble_task_context.py",
      "qual_name": "_weight",
      "short_name": "_weight",
      "line": 145,
      "context": "def _weight(intent: str) -> float:",
      "confidence": "low (test usage)",
      "reason": "No references found (short=1, qual=1) [USED IN TESTS]",
      "in_tests": true,
      "in_strings": false
    },
    {
      "file": "src/jcodemunch_mcp/tools/assemble_task_context.py",
      "qual_name": "assemble_task_context",
      "short_name": "assemble_task_context",
      "line": 255,
      "context": "def assemble_task_context(",
      "confidence": "low (test usage)",
      "reason": "No references found (short=1, qual=1) [USED IN TESTS]",
      "in_tests": true,
      "in_strings": true
    },
    {
      "file": "src/jcodemunch_mcp/tools/embed_repo.py",
      "qual_name": "embed_repo",
      "short_name": "embed_repo",
      "line": 203,
      "context": "def embed_repo(",
      "confidence": "low (test usage)",
      "reason": "No references found (short=1, qual=1) [USED IN TESTS]",
      "in_tests": true,
      "in_strings": true
    },
    {
      "file": "src/jcodemunch_mcp/tools/get_class_hierarchy.py",
      "qual_name": "get_class_hierarchy",
      "short_name": "get_class_hierarchy",
      "line": 69,
      "context": "def get_class_hierarchy(",
      "confidence": "low (test usage)",
      "reason": "No references found (short=1, qual=1) [USED IN TESTS]",
      "in_tests": true,
      "in_strings": true
    },
    {
      "file": "src/jcodemunch_mcp/tools/get_dependency_graph.py",
      "qual_name": "get_dependency_graph",
      "short_name": "get_dependency_graph",
      "line": 34,
      "context": "def get_dependency_graph(",
      "confidence": "low (test usage)",
      "reason": "No references found (short=1, qual=1) [USED IN TESTS]",
      "in_tests": true,
      "in_strings": true
    },
    {
      "file": "src/jcodemunch_mcp/tools/get_project_intel.py",
      "qual_name": "get_project_intel",
      "short_name": "get_project_intel",
      "line": 942,
      "context": "def get_project_intel(",
      "confidence": "low (test usage)",
      "reason": "No references found (short=1, qual=1) [USED IN TESTS]",
      "in_tests": true,
      "in_strings": true
    },
    {
      "file": "src/jcodemunch_mcp/tools/get_symbol_complexity.py",
      "qual_name": "get_symbol_complexity",
      "short_name": "get_symbol_complexity",
      "line": 25,
      "context": "def get_symbol_complexity(",
      "confidence": "low (test usage)",
      "reason": "No references found (short=1, qual=1) [USED IN TESTS]",
      "in_tests": true,
      "in_strings": true
    },
    {
      "file": "src/jcodemunch_mcp/tools/get_symbol_provenance.py",
      "qual_name": "get_symbol_provenance",
      "short_name": "get_symbol_provenance",
      "line": 202,
      "context": "def get_symbol_provenance(",
      "confidence": "low (test usage)",
      "reason": "No references found (short=1, qual=1) [USED IN TESTS]",
      "in_tests": true,
      "in_strings": true
    },
    {
      "file": "src/jcodemunch_mcp/tools/health_radar.py",
      "qual_name": "diff_health_radar",
      "short_name": "diff_health_radar",
      "line": 312,
      "context": "def diff_health_radar(baseline: dict, current: dict) -> dict:",
      "confidence": "low (test usage)",
      "reason": "No references found (short=0, qual=0) [USED IN TESTS]",
      "in_tests": true,
      "in_strings": false
    },
    {
      "file": "src/jcodemunch_mcp/tools/index_folder.py",
      "qual_name": "_CarriedSymbol.__getattr__",
      "short_name": "__getattr__",
      "line": 416,
      "context": "def __getattr__(self, name: str):",
      "confidence": "low (test usage)",
      "reason": "No references found (short=0, qual=0) [USED IN TESTS]",
      "in_tests": true,
      "in_strings": false
    },
    {
      "file": "src/jcodemunch_mcp/tools/index_folder.py",
      "qual_name": "_resolve_repo_identity",
      "short_name": "_resolve_repo_identity",
      "line": 544,
      "context": "def _resolve_repo_identity(",
      "confidence": "low (test usage)",
      "reason": "No references found (short=0, qual=0) [USED IN TESTS]",
      "in_tests": true,
      "in_strings": false
    },
    {
      "file": "src/jcodemunch_mcp/tools/list_workspaces.py",
      "qual_name": "list_workspaces",
      "short_name": "list_workspaces",
      "line": 445,
      "context": "def list_workspaces(",
      "confidence": "low (test usage)",
      "reason": "No references found (short=1, qual=1) [USED IN TESTS]",
      "in_tests": true,
      "in_strings": true
    },
    {
      "file": "src/jcodemunch_mcp/tools/plan_refactoring.py",
      "qual_name": "plan_refactoring",
      "short_name": "plan_refactoring",
      "line": 314,
      "context": "def plan_refactoring(",
      "confidence": "low (test usage)",
      "reason": "No references found (short=1, qual=1) [USED IN TESTS]",
      "in_tests": true,
      "in_strings": true
    },
    {
      "file": "src/jcodemunch_mcp/tools/register_edit.py",
      "qual_name": "register_edit",
      "short_name": "register_edit",
      "line": 13,
      "context": "def register_edit(",
      "confidence": "low (test usage)",
      "reason": "No references found (short=1, qual=1) [USED IN TESTS]",
      "in_tests": true,
      "in_strings": true
    },
    {
      "file": "src/jcodemunch_mcp/tools/search_ast.py",
      "qual_name": "search_ast",
      "short_name": "search_ast",
      "line": 1000,
      "context": "def search_ast(",
      "confidence": "low (test usage)",
      "reason": "No references found (short=1, qual=1) [USED IN TESTS]",
      "in_tests": true,
      "in_strings": true
    },
    {
      "file": "src/jcodemunch_mcp/tools/search_columns.py",
      "qual_name": "search_columns",
      "short_name": "search_columns",
      "line": 29,
      "context": "def search_columns(",
      "confidence": "low (test usage)",
      "reason": "No references found (short=1, qual=1) [USED IN TESTS]",
      "in_tests": true,
      "in_strings": true
    },
    {
      "file": "src/jcodemunch_mcp/tools/search_text.py",
      "qual_name": "search_text",
      "short_name": "search_text",
      "line": 54,
      "context": "def search_text(",
      "confidence": "low (test usage)",
      "reason": "No references found (short=1, qual=1) [USED IN TESTS]",
      "in_tests": true,
      "in_strings": true
    },
    {
      "file": "src/jcodemunch_mcp/tools/summarize_repo.py",
      "qual_name": "summarize_repo",
      "short_name": "summarize_repo",
      "line": 39,
      "context": "def summarize_repo(",
      "confidence": "low (test usage)",
      "reason": "No references found (short=1, qual=1) [USED IN TESTS]",
      "in_tests": true,
      "in_strings": true
    },
    {
      "file": "src/jcodemunch_mcp/tools/turn_budget.py",
      "qual_name": "TurnBudget.is_new_turn",
      "short_name": "is_new_turn",
      "line": 38,
      "context": "def is_new_turn(self) -> bool:",
      "confidence": "low (test usage)",
      "reason": "No references found (short=0, qual=0) [USED IN TESTS]",
      "in_tests": true,
      "in_strings": false
    },
    {
      "file": "src/jcodemunch_mcp/tools/turn_budget.py",
      "qual_name": "TurnBudget.percent_used",
      "short_name": "percent_used",
      "line": 92,
      "context": "def percent_used(self) -> float:",
      "confidence": "low (test usage)",
      "reason": "No references found (short=0, qual=0) [USED IN TESTS]",
      "in_tests": true,
      "in_strings": false
    },
    {
      "file": "src/jcodemunch_mcp/tools/turn_budget.py",
      "qual_name": "TurnBudget.reset",
      "short_name": "reset",
      "line": 118,
      "context": "def reset(self) -> None:",
      "confidence": "low (test usage)",
      "reason": "No references found (short=0, qual=0) [USED IN TESTS]",
      "in_tests": true,
      "in_strings": true
    },
    {
      "file": "src/jcodemunch_mcp/watcher.py",
      "qual_name": "_folder_hash",
      "short_name": "_folder_hash",
      "line": 109,
      "context": "def _folder_hash(folder_path: str) -> str:",
      "confidence": "low (test usage)",
      "reason": "No references found (short=0, qual=0) [USED IN TESTS]",
      "in_tests": true,
      "in_strings": false
    }
  ]
}